third_sdk/__init__.py
third_sdk/api/__init__.py
third_sdk/api/doudian_api/__init__.py
third_sdk/api/doudian_api/base.py
third_sdk/api/jd_api/__init__.py
third_sdk/api/jd_api/base.py
third_sdk/api/pdd_api/__init__.py
third_sdk/api/pdd_api/base.py
third_sdk/api/tb_api/__init__.py
third_sdk/api/tb_api/base.py
third_sdk/api/vip_api/__init__.py
third_sdk/api/vip_api/base.py
third_sdk/jd/__init__.py
third_sdk/jd/api/__init__.py
third_sdk/jd/api/base.py
third_sdk/jd/api/rest/AddressAllProvincesQueryRequest.py
third_sdk/jd/api/rest/AddressCitysByProvinceIdQueryRequest.py
third_sdk/jd/api/rest/AddressCountysByCityIdQueryRequest.py
third_sdk/jd/api/rest/AddressTownsByCountyIdQueryRequest.py
third_sdk/jd/api/rest/AfterSaleAfsApplyCreateRequest.py
third_sdk/jd/api/rest/AfterSaleAuditCancelQueryRequest.py
third_sdk/jd/api/rest/AfterSaleAvailableNumberCompQueryRequest.py
third_sdk/jd/api/rest/AfterSaleCustomerExpectCompQueryRequest.py
third_sdk/jd/api/rest/AfterSaleSendSkuUpdateRequest.py
third_sdk/jd/api/rest/AfterSaleServiceDetailInfoQueryRequest.py
third_sdk/jd/api/rest/AfterSaleServiceListPageQueryRequest.py
third_sdk/jd/api/rest/AfterSaleWareReturnJdCompQueryRequest.py
third_sdk/jd/api/rest/BizAreaGetJDAddressFromAddressRequest.py
third_sdk/jd/api/rest/BizProductGetSimilarSkuRequest.py
third_sdk/jd/api/rest/BizProductGetSkuByPageRequest.py
third_sdk/jd/api/rest/BizProductGetcategoryRequest.py
third_sdk/jd/api/rest/BizProductGetcategorysRequest.py
third_sdk/jd/api/rest/InvoiceQueryRequest.py
third_sdk/jd/api/rest/InvoiceSubmitRequest.py
third_sdk/jd/api/rest/InvoiceWaybillRequest.py
third_sdk/jd/api/rest/JosMasterKeyGetRequest.py
third_sdk/jd/api/rest/JosSecretApiReportGetRequest.py
third_sdk/jd/api/rest/JosVoucherInfoGetRequest.py
third_sdk/jd/api/rest/JsfXbXBProductServiceQueryProductsRequest.py
third_sdk/jd/api/rest/KeplerItemGetnologinpromotionRequest.py
third_sdk/jd/api/rest/KeplerItemQuerybigfieldconvertskuRequest.py
cps_sdk-0.0.5.dist-info/LICENSE
cps_sdk-0.0.5.dist-info/METADATA
cps_sdk-0.0.5.dist-info/WHEEL
cps_sdk-0.0.5.dist-info/top_level.txt
cps_sdk-0.0.5.dist-info/zip-safe
cps_sdk-0.0.5.dist-info/RECORD
